icon_generator/__init__.py
icon_generator/errors/__init__.py
icon_generator/errors/error_message.py
icon_generator/generator/__init__.py
icon_generator/generator/generator.py
icon_generator/generator/git/__init__.py
icon_generator/generator/git/core/__init__.py
icon_generator/generator/git/core/color/__init__.py
icon_generator/generator/git/core/color/hsl_converter.py
icon_generator/generator/git/core/color/rgb_generator.py
icon_generator/generator/git/core/pattern/__init__.py
icon_generator/generator/git/core/pattern/pattern_generator.py
icon_generator/generator/git/git_icon_generator.py
icon_generator-0.1.0.dist-info/LICENSE.md
icon_generator-0.1.0.dist-info/METADATA
icon_generator-0.1.0.dist-info/WHEEL
icon_generator-0.1.0.dist-info/RECORD
