Metadata-Version: 2.3
Name: icon-generator
Version: 0.1.0
Summary: This package generates various icons.
License: MIT License
Author: pochimoritaro
Author-email: pochimoritaro@gmail.com
Requires-Python: >=3.12
Classifier: License :: Other/Proprietary License
Classifier: Programming Language :: Python :: 3
Classifier: Programming Language :: Python :: 3.12
Classifier: Programming Language :: Python :: 3.13
Requires-Dist: numpy (>=2.1.3)
Requires-Dist: pillow (>=11.1.0)
